joye/__init__.py
joye/consts.py
joye/logger.py
joye/oss.py
joye-0.1.3.dist-info/LICENSE
joye-0.1.3.dist-info/WHEEL
joye-0.1.3.dist-info/METADATA
joye-0.1.3.dist-info/RECORD
