Metadata-Version: 2.1
Name: joye
Version: 0.1.3
Summary: Python SDK for Joye
Author-email: jyfund <jingchaohu@gmail.com>
Classifier: License :: OSI Approved :: MIT License
Requires-Dist: oss2 == 2.16.0
